__init__.py
core/__init__.py
core/protocols.py
polydb-0.0.0.dist-info/METADATA
polydb-0.0.0.dist-info/WHEEL
polydb-0.0.0.dist-info/top_level.txt
polydb-0.0.0.dist-info/RECORD
